anyblok_bus/__init__.py
anyblok_bus/adapter.py
anyblok_bus/config.py
anyblok_bus/consumer.py
anyblok_bus/release.py
anyblok_bus/scripts.py
anyblok_bus/status.py
anyblok_bus/worker.py
anyblok_bus/bloks/__init__.py
anyblok_bus/bloks/bus/CODE.rst
anyblok_bus/bloks/bus/README.rst
anyblok_bus/bloks/bus/__init__.py
anyblok_bus/bloks/bus/bus.py
anyblok_bus/bloks/bus/exceptions.py
anyblok_bus/bloks/bus/message.py
anyblok_bus/bloks/bus/profile.py
anyblok_bus/bloks/traces/CODE.rst
anyblok_bus/bloks/traces/README.rst
anyblok_bus/bloks/traces/__init__.py
anyblok_bus/bloks/traces/trace.py
anyblok_bus/tests/__init__.py
anyblok_bus/tests/test_consumer.py
anyblok_bus/tests/test_low_level.py
anyblok_bus/tests/test_message.py
anyblok_bus-1.2.0.dist-info/LICENSE.rst
anyblok_bus-1.2.0.dist-info/METADATA
anyblok_bus-1.2.0.dist-info/WHEEL
anyblok_bus-1.2.0.dist-info/entry_points.txt
anyblok_bus-1.2.0.dist-info/top_level.txt
anyblok_bus-1.2.0.dist-info/RECORD
