Metadata-Version: 2.1
Name: anyblok-bus
Version: 1.2.0
Summary: Bus for anyblok
Home-page: http://docs.anyblok-bus.anyblok.org/1.2.0
Author: jssuzanne
Author-email: jssuzanne@anybox.fr
License: UNKNOWN
Keywords: bus
Platform: UNKNOWN
Classifier: Development Status :: 5 - Production/Stable
Classifier: Intended Audience :: Developers
Classifier: Programming Language :: Python :: 3
Classifier: Programming Language :: Python :: 3.4
Classifier: Programming Language :: Python :: 3.5
Classifier: Programming Language :: Python :: 3.6
Classifier: Programming Language :: Python :: 3.7
Classifier: Programming Language :: Python :: 3.8
Requires-Dist: anyblok
Requires-Dist: furl
Requires-Dist: marshmallow (>=3.0.0rc5)
Requires-Dist: pika (>=1.0.1)
